tiny_haversine-0.1.1.dist-info/WHEEL
tiny_haversine-0.1.1.dist-info/top_level.txt
tiny_haversine-0.1.1.dist-info/METADATA
tiny_haversine-0.1.1.dist-info/RECORD
tiny_haversine-0.1.1.dist-info/licenses/LICENSE
tiny_haversine/_haversine.cpython-312-i386-linux-gnu.so
tiny_haversine/__init__.py
tiny_haversine/_haversine.c
