Metadata-Version: 2.4
Name: tiny-haversine
Version: 0.1.1
Summary: Tiny C-extension haversine example
License-Expression: Apache-2.0
Requires-Python: >=3.10
License-File: LICENSE
Dynamic: license-file
